LICENSE
README.md
setup.py
media/r245.png
r245/__init__.py
r245.egg-info/PKG-INFO
r245.egg-info/SOURCES.txt
r245.egg-info/dependency_links.txt
r245.egg-info/entry_points.txt
r245.egg-info/not-zip-safe
r245.egg-info/requires.txt
r245.egg-info/top_level.txt