Metadata-Version: 1.0
Name: r245
Version: 2021.11.23.1048
Summary: kill blacklisted programs on high volatile memory usage
Home-page: https://github.com/wdbm/r245
Author: Will Breaden Madden, Gavin Kirby
Author-email: wbm@protonmail.ch, clean_air_turbulence@protonmail.com
License: GPLv3
Platform: UNKNOWN
